ddr_davis_data/PIV_2D.py
ddr_davis_data/__init__.py
ddr_davis_data/base.py
ddr_davis_data/plotting.py
ddr_davis_data/shared.py
ddr_davis_data/utils.py
ddr_davis_data/version.py
ddr_davis_data-0.1.25.dist-info/LICENSE.txt
ddr_davis_data-0.1.25.dist-info/METADATA
ddr_davis_data-0.1.25.dist-info/WHEEL
ddr_davis_data-0.1.25.dist-info/top_level.txt
ddr_davis_data-0.1.25.dist-info/RECORD
