Metadata-Version: 2.1
Name: ddr_davis_data
Version: 0.1.25
Summary: Package to handle davis data files
Home-page: https://github.com/ddrathod121294/ddr_davis_data
Author: Darshan Rathod
Author-email: darshan.rathod1994@gmail.com
Keywords: ddr,davis,davis_data,davis_data_manager,ddr_davis_data
Classifier: Development Status :: 2 - Pre-Alpha
Classifier: Intended Audience :: Education
Classifier: Intended Audience :: Science/Research
Classifier: Natural Language :: English
Classifier: License :: OSI Approved :: MIT License
Classifier: Topic :: Education
Classifier: Topic :: Scientific/Engineering
Classifier: Topic :: Scientific/Engineering :: Physics
Classifier: Programming Language :: Python :: 3.10
Requires-Python: >=3.10, <4
License-File: LICENSE.txt
Requires-Dist: numpy
Requires-Dist: pandas
Requires-Dist: matplotlib
Requires-Dist: openpyxl
